docs/Makefile
docs/changelog.rst
docs/cli.rst
docs/conf.py
docs/contributing.rst
docs/index.rst
docs/library.rst
docs/requirements.txt
docs/api/cli.rst
docs/api/combine.rst
docs/api/exceptions.rst
docs/api/mapping_sheet.rst
docs/api/packager.rst
docs/api/schema.rst
docs/api/upgrade.rst
docs/api/util.rst
docs/cli/examples.rst
docs/cli/generic.rst
docs/cli/ocds.rst
docs/cli/schema.rst
ocdskit/__init__.py
ocdskit/__main__.py
ocdskit/combine.py
ocdskit/exceptions.py
ocdskit/mapping_sheet.py
ocdskit/packager.py
ocdskit/schema.py
ocdskit/upgrade.py
ocdskit/util.py
ocdskit/commands/__init__.py
ocdskit/commands/base.py
ocdskit/commands/combine_record_packages.py
ocdskit/commands/combine_release_packages.py
ocdskit/commands/compile.py
ocdskit/commands/detect_format.py
ocdskit/commands/echo.py
ocdskit/commands/indent.py
ocdskit/commands/mapping_sheet.py
ocdskit/commands/package_records.py
ocdskit/commands/package_releases.py
ocdskit/commands/schema_report.py
ocdskit/commands/schema_strict.py
ocdskit/commands/set_closed_codelist_enums.py
ocdskit/commands/split_record_packages.py
ocdskit/commands/split_release_packages.py
ocdskit/commands/upgrade.py
ocdskit-1.5.0.dist-info/licenses/LICENSE
ocdskit-1.5.0.dist-info/METADATA
ocdskit-1.5.0.dist-info/WHEEL
ocdskit-1.5.0.dist-info/entry_points.txt
ocdskit-1.5.0.dist-info/top_level.txt
ocdskit-1.5.0.dist-info/RECORD
