Metadata-Version: 2.4
Name: ocdskit
Version: 1.5.0
Summary: A suite of command-line tools for working with OCDS data
Author-email: Open Contracting Partnership <data@open-contracting.org>
License: BSD
Project-URL: Homepage, https://github.com/open-contracting/ocdskit
Classifier: License :: OSI Approved :: BSD License
Classifier: Operating System :: OS Independent
Classifier: Programming Language :: Python :: 3.10
Classifier: Programming Language :: Python :: 3.11
Classifier: Programming Language :: Python :: 3.12
Classifier: Programming Language :: Python :: 3.13
Classifier: Programming Language :: Python :: Implementation :: CPython
Classifier: Programming Language :: Python :: Implementation :: PyPy
License-File: LICENSE
Requires-Dist: ijson>=2.5
Requires-Dist: jsonref
Requires-Dist: ocdsmerge>=0.6
Requires-Dist: ocdsextensionregistry>=0.6.7
Provides-Extra: perf
Requires-Dist: orjson>=3; extra == "perf"
Provides-Extra: test
Requires-Dist: coverage; extra == "test"
Requires-Dist: jsonpointer; extra == "test"
Requires-Dist: libcove==0.32.1; extra == "test"
Requires-Dist: pytest; extra == "test"
Requires-Dist: pytest-benchmark; extra == "test"
Dynamic: license-file
